lokermed_auth_lib/__init__.py
lokermed_auth_lib/auth.py
lokermed_auth_lib-0.1.0.dist-info/METADATA
lokermed_auth_lib-0.1.0.dist-info/WHEEL
lokermed_auth_lib-0.1.0.dist-info/top_level.txt
lokermed_auth_lib-0.1.0.dist-info/RECORD
