Metadata-Version: 2.1
Name: lokermed-auth-lib
Version: 0.1.0
Summary: Libsssss
Author: mrizkyff
License: MIT
